spirallogic/__init__.py
spirallogic/spirallogic_cli.py
spirallogic/spirallogic_parser_v2.py
spirallogic/spirallogic_runtime.py
spirallogic/spirallogic_stdlib.py
spirallogic/unicode_sanitizer.py
spirallogic-0.1.1.dist-info/licenses/LICENSE
spirallogic-0.1.1.dist-info/METADATA
spirallogic-0.1.1.dist-info/WHEEL
spirallogic-0.1.1.dist-info/entry_points.txt
spirallogic-0.1.1.dist-info/top_level.txt
spirallogic-0.1.1.dist-info/RECORD
