Metadata-Version: 2.4
Name: spirallogic
Version: 0.1.1
Summary: A consciousness-aware programming language for ethical AI interaction
Author-email: Your Name <your.email@example.com>
License: MIT License
Requires-Python: >=3.8
License-File: LICENSE
Requires-Dist: requests
Dynamic: license-file
